conf_root/ConfRoot.py
conf_root/Configuration.py
conf_root/__init__.py
conf_root/run_http.py
conf_root/utils.py
conf_root/agents/BasicAgent.py
conf_root/agents/JsonAgent.py
conf_root/agents/YamlAgent.py
conf_root/agents/utils.py
conf_root/templates/form.html
conf_root/templates/index.html
conf_root-0.5.0.dist-info/LICENSE
conf_root-0.5.0.dist-info/METADATA
conf_root-0.5.0.dist-info/WHEEL
conf_root-0.5.0.dist-info/entry_points.txt
conf_root-0.5.0.dist-info/top_level.txt
conf_root-0.5.0.dist-info/RECORD
