Metadata-Version: 2.1
Name: conf_root
Version: 0.5.0
Summary: 基于dataclass的科研配置文件取用工具
Home-page: https://github.com/ciaranchen/conf_root
Author: ciaranchen
Author-email: ciaranchen <ciaranchen@qq.com>
License: MIT
Requires-Python: >=3.9
License-File: LICENSE
Requires-Dist: ruamel-yaml>=0.18.6
Requires-Dist: wtforms>=3.1.2
Requires-Dist: jinja2>=3.1.4
